dbt/adapters/starburst/__init__.py
dbt/adapters/starburst/__version__.py
dbt/adapters/starburst/column.py
dbt/adapters/starburst/connections.py
dbt/adapters/starburst/impl.py
dbt/adapters/starburst/relation.py
dbt/include/trino/__init__.py
dbt_starburst-1.0.0.dist-info/LICENSE.txt
dbt_starburst-1.0.0.dist-info/METADATA
dbt_starburst-1.0.0.dist-info/WHEEL
dbt_starburst-1.0.0.dist-info/top_level.txt
dbt_starburst-1.0.0.dist-info/RECORD
