Metadata-Version: 2.1
Name: dbt-starburst
Version: 1.0.0
Summary: The Starburst adapter plugin for dbt (data build tool)
Home-page: https://github.com/starburstdata/dbt-starburst
Author: Starburst Data
Author-email: info@starburstdata.com
License: Apache License 2.0
Platform: any
Classifier: Development Status :: 5 - Production/Stable
Classifier: License :: OSI Approved :: Apache Software License
Classifier: Operating System :: Microsoft :: Windows
Classifier: Operating System :: MacOS :: MacOS X
Classifier: Operating System :: POSIX :: Linux
Classifier: Programming Language :: Python :: 3.7
Classifier: Programming Language :: Python :: 3.8
Classifier: Programming Language :: Python :: 3.9
Classifier: Programming Language :: Python :: 3.10
Classifier: Programming Language :: Python :: 3.11
Requires-Python: >=3.7
License-File: LICENSE.txt
Requires-Dist: dbt-core (~=1.0.0)
Requires-Dist: trino (~=0.322)
